{"count":4,"results":[{"listing_id":188237487,"state":"active","user_id":5777500,"category_id":69160159,"title":"Raw Natural Arkansas Quartz Neckwear","description":" Self Healed Quartz is Simple yet has a Modern wire wrapped. Natural Arkansas quartz point is a great energy balancer and amplier. Google self healed Quartz to learn more about this beautiful Quartz an its properties. \n\nmade by me with love\n","creation_tsz":1419894548,"ending_tsz":1430345348,"original_creation_tsz":1398999630,"last_modified_tsz":1420122409,"price":"75.00","currency_code":"USD","quantity":1,"tags":["healing","Metaphysics","energy","raw","chakra","Jewelry","organic","Minerals","handmade","Quartz","copper","Balance","Ooak"],"category_path":["Jewelry","Necklace","Metalwork"],"category_path_ids":[68887482,69151567,69160159],"materials":[],"shop_section_id":14779178,"featured_rank":12,"state_tsz":1399691992,"url":"https:\/\/www.etsy.com\/listing\/188237487\/raw-natural-arkansas-quartz-neckwear?utm_source=reworkcreativeonetsy&utm_medium=api&utm_campaign=api","views":130,"num_favorers":8,"shipping_template_id":3152165856,"processing_min":5,"processing_max":10,"who_made":"i_did","is_supply":"false","when_made":"2010_2015","is_private":false,"recipient":null,"occasion":null,"style":null,"non_taxable":false,"is_customizable":false,"is_digital":false,"file_data":"","language":"en-US","has_variations":false,"used_manufacturer":false,"Images":[{"listing_image_id":704422049,"hex_code":"66646A","red":102,"green":100,"blue":106,"hue":260,"saturation":5,"brightness":41,"is_black_and_white":false,"creation_tsz":1419894993,"listing_id":188237487,"rank":1,"url_75x75":"https:\/\/img1.etsystatic.com\/045\/0\/5406120\/il_75x75.704422049_99tn.jpg","url_170x135":"https:\/\/img1.etsystatic.com\/045\/0\/5406120\/il_170x135.704422049_99tn.jpg","url_570xN":"https:\/\/img1.etsystatic.com\/045\/0\/5406120\/il_570xN.704422049_99tn.jpg","url_fullxfull":"https:\/\/img1.etsystatic.com\/045\/0\/5406120\/il_fullxfull.704422049_99tn.jpg","full_height":1500,"full_width":1125},{"listing_image_id":704296736,"hex_code":"BFB8B5","red":191,"green":184,"blue":181,"hue":18,"saturation":5,"brightness":74,"is_black_and_white":false,"creation_tsz":1419894549,"listing_id":188237487,"rank":2,"url_75x75":"https:\/\/img0.etsystatic.com\/045\/0\/5406120\/il_75x75.704296736_gzm5.jpg","url_170x135":"https:\/\/img0.etsystatic.com\/045\/0\/5406120\/il_170x135.704296736_gzm5.jpg","url_570xN":"https:\/\/img0.etsystatic.com\/045\/0\/5406120\/il_570xN.704296736_gzm5.jpg","url_fullxfull":"https:\/\/img0.etsystatic.com\/045\/0\/5406120\/il_fullxfull.704296736_gzm5.jpg","full_height":1500,"full_width":1500},{"listing_image_id":704296748,"hex_code":"B8B0AB","red":184,"green":176,"blue":171,"hue":23,"saturation":7,"brightness":72,"is_black_and_white":false,"creation_tsz":1419894549,"listing_id":188237487,"rank":3,"url_75x75":"https:\/\/img0.etsystatic.com\/051\/0\/5406120\/il_75x75.704296748_g8pa.jpg","url_170x135":"https:\/\/img0.etsystatic.com\/051\/0\/5406120\/il_170x135.704296748_g8pa.jpg","url_570xN":"https:\/\/img0.etsystatic.com\/051\/0\/5406120\/il_570xN.704296748_g8pa.jpg","url_fullxfull":"https:\/\/img0.etsystatic.com\/051\/0\/5406120\/il_fullxfull.704296748_g8pa.jpg","full_height":1500,"full_width":1125}]},{"listing_id":214328064,"state":"active","user_id":5777500,"category_id":69160197,"title":"Amazonite with Copper Wire Wrap Pendant ","description":"This Organically wrap Amazonite Pendant is unique and special! Made with positive vibes and good intent!\r\n\r\n\r\nThis pic is an example of the style pendant you will be receiving...  Amazonite Meaning\r\n\r\nThis semi-opaque blue-green variety of feldspar is named after the Amazon River.\r\n\r\nAmazonite balances feminine and masculine energy. It promotes kindness and practicality. It is an excellent stone for artists and for men.\r\n\r\nPale azure blue amazonite is know as the lucky &quot;Hope Stone&quot;. It will be lucky for all your hopes and dreams. Amazonite is blue-green to pale green stone in the feldspar group. It comes mainly from United States and Australia.\r\n\r\nHealing properties of amazonite\r\n\r\nAmazonite helps balance the emotions and gives physical stamina","creation_tsz":1417935839,"ending_tsz":1428386639,"original_creation_tsz":1417923180,"last_modified_tsz":1420122988,"price":"37.50","currency_code":"USD","quantity":9,"tags":["crystals","stones","ring","copper","healing","handmade","chakra","organic","custom","trend","raw","energy","quartzcluster"],"category_path":["Jewelry","Ring","Metalwork"],"category_path_ids":[68887482,69152047,69160197],"materials":["Copper","brass","metal","wire","crystals","stones","minerals","rocks","quartzpoints","leather"],"shop_section_id":14779178,"featured_rank":11,"state_tsz":1417923181,"url":"https:\/\/www.etsy.com\/listing\/214328064\/amazonite-with-copper-wire-wrap-pendant?utm_source=reworkcreativeonetsy&utm_medium=api&utm_campaign=api","views":111,"num_favorers":5,"shipping_template_id":3152165856,"processing_min":5,"processing_max":10,"who_made":"i_did","is_supply":"false","when_made":"made_to_order","is_private":false,"recipient":null,"occasion":null,"style":["Boho"],"non_taxable":false,"is_customizable":false,"is_digital":false,"file_data":"","language":"en-US","has_variations":true,"used_manufacturer":false,"Images":[{"listing_image_id":696289316,"hex_code":"C4C7C5","red":196,"green":199,"blue":197,"hue":140,"saturation":1,"brightness":78,"is_black_and_white":false,"creation_tsz":1418058448,"listing_id":214328064,"rank":1,"url_75x75":"https:\/\/img0.etsystatic.com\/047\/0\/5406120\/il_75x75.696289316_e7ho.jpg","url_170x135":"https:\/\/img0.etsystatic.com\/047\/0\/5406120\/il_170x135.696289316_e7ho.jpg","url_570xN":"https:\/\/img0.etsystatic.com\/047\/0\/5406120\/il_570xN.696289316_e7ho.jpg","url_fullxfull":"https:\/\/img0.etsystatic.com\/047\/0\/5406120\/il_fullxfull.696289316_e7ho.jpg","full_height":1500,"full_width":1500},{"listing_image_id":695686069,"hex_code":"A17A54","red":161,"green":122,"blue":84,"hue":30,"saturation":47,"brightness":63,"is_black_and_white":false,"creation_tsz":1417923602,"listing_id":214328064,"rank":2,"url_75x75":"https:\/\/img1.etsystatic.com\/055\/0\/5406120\/il_75x75.695686069_ih9u.jpg","url_170x135":"https:\/\/img1.etsystatic.com\/055\/0\/5406120\/il_170x135.695686069_ih9u.jpg","url_570xN":"https:\/\/img1.etsystatic.com\/055\/0\/5406120\/il_570xN.695686069_ih9u.jpg","url_fullxfull":"https:\/\/img1.etsystatic.com\/055\/0\/5406120\/il_fullxfull.695686069_ih9u.jpg","full_height":919,"full_width":699}]},{"listing_id":194865882,"state":"active","user_id":5777500,"category_id":68887482,"title":"Simple Unisex Brazilian Quartz Neckwear","description":"Simple Unisex Quartz Neckwear\n-------------\u00bb\u25b2\u00abBoho-Chic Style\u00bb\u25b2\u00ab------------\r\n\r\nOrganically inspired-by-nature accessories like this Stunning Lemurian  Crystal Quartz Necklace, so unique and beautiful, So Chic!!!. It&#39;s such a statement stunner and touches on so many different looks, boho, natural, tribal and spiritual...\r\n............This crystal will fill your soul with light and positive energy.\r\n\r\nQuartz pendant: the size of the crystal varies depends of the Mother Nature\r\n(no crystals are the same)\r\n\r\nYour necklace will be similar to the one picture\r\nEach piece is made with so much love, very special and unique!!\r\n\r\nAll my items have been individually hand-picked and carefully selected for their uniqueness, quality, and style.\r\n\r\nCreated with the love and light of a free spirit\n\nCreated with;\r\n\u25b2rough lemurian crystal quartz from Brazil\r\n\u25b2deer skin leather \r\n\u25b2pendant: approx. 2 1\/2&quot;\r\n\u25b2necklace approx. 20&quot; long\r\n\n&lt;---\u00bb\u25b2\u00ab---&gt;\r\nClear Quartz is a conductor of energy - both as a receiver and a transmitter. It helps you feel re-energized and happier with harmony towards others, It helps focus the mind and aids meditation by filtering out distractions,\r\nCrystals have been used for healing the body, transforming the spirit, inspiring intuitive insight, guarding against negative vibrations, and smoothing the energy flows of spirit and body...\r\nIt is important to keep your crystal clean in order to protect it from outside negative vibrations, Your personal crystals will attune themselves to your vibrations, as you will attune to the natural vibrations of the crystal.\r\n\r\nDeer:\r\nThe deer has graceful features and delicate movements, symbolizes Love\r\nGrace, Peace, Beauty, Fertility, Humility, Swiftness, Regrowth, Creativity, Spirituality and Abundance\n\nUnisex","creation_tsz":1415687168,"ending_tsz":1426051568,"original_creation_tsz":1404181171,"last_modified_tsz":1415767300,"price":"60.00","currency_code":"USD","quantity":30,"tags":["Minimal","Jewels","Metaphysics","Stones","Handmade","Bohemian","Jewelry","Minerals","Healing","Quartz","Balance","Trend"],"category_path":["Jewelry"],"category_path_ids":[68887482],"materials":[],"shop_section_id":14779178,"featured_rank":null,"state_tsz":1414808421,"url":"https:\/\/www.etsy.com\/listing\/194865882\/simple-unisex-brazilian-quartz-neckwear?utm_source=reworkcreativeonetsy&utm_medium=api&utm_campaign=api","views":235,"num_favorers":12,"shipping_template_id":5668078,"processing_min":5,"processing_max":10,"who_made":"i_did","is_supply":"false","when_made":"2010_2015","is_private":false,"recipient":null,"occasion":null,"style":null,"non_taxable":false,"is_customizable":false,"is_digital":false,"file_data":"","language":"en-US","has_variations":false,"used_manufacturer":false,"Images":[{"listing_image_id":621605319,"hex_code":"9D7C6D","red":157,"green":124,"blue":109,"hue":19,"saturation":30,"brightness":61,"is_black_and_white":false,"creation_tsz":1404181171,"listing_id":194865882,"rank":1,"url_75x75":"https:\/\/img1.etsystatic.com\/044\/0\/5406120\/il_75x75.621605319_6x1f.jpg","url_170x135":"https:\/\/img1.etsystatic.com\/044\/0\/5406120\/il_170x135.621605319_6x1f.jpg","url_570xN":"https:\/\/img1.etsystatic.com\/044\/0\/5406120\/il_570xN.621605319_6x1f.jpg","url_fullxfull":"https:\/\/img1.etsystatic.com\/044\/0\/5406120\/il_fullxfull.621605319_6x1f.jpg","full_height":1136,"full_width":756},{"listing_image_id":621605357,"hex_code":"895947","red":137,"green":89,"blue":71,"hue":16,"saturation":48,"brightness":53,"is_black_and_white":false,"creation_tsz":1404181171,"listing_id":194865882,"rank":2,"url_75x75":"https:\/\/img1.etsystatic.com\/043\/0\/5406120\/il_75x75.621605357_5b1g.jpg","url_170x135":"https:\/\/img1.etsystatic.com\/043\/0\/5406120\/il_170x135.621605357_5b1g.jpg","url_570xN":"https:\/\/img1.etsystatic.com\/043\/0\/5406120\/il_570xN.621605357_5b1g.jpg","url_fullxfull":"https:\/\/img1.etsystatic.com\/043\/0\/5406120\/il_fullxfull.621605357_5b1g.jpg","full_height":852,"full_width":1136},{"listing_image_id":621605447,"hex_code":"8E6352","red":142,"green":99,"blue":82,"hue":17,"saturation":42,"brightness":55,"is_black_and_white":false,"creation_tsz":1404181171,"listing_id":194865882,"rank":3,"url_75x75":"https:\/\/img1.etsystatic.com\/028\/0\/5406120\/il_75x75.621605447_gwly.jpg","url_170x135":"https:\/\/img1.etsystatic.com\/028\/0\/5406120\/il_170x135.621605447_gwly.jpg","url_570xN":"https:\/\/img1.etsystatic.com\/028\/0\/5406120\/il_570xN.621605447_gwly.jpg","url_fullxfull":"https:\/\/img1.etsystatic.com\/028\/0\/5406120\/il_fullxfull.621605447_gwly.jpg","full_height":1136,"full_width":1136}]},{"listing_id":209305220,"state":"active","user_id":5777500,"category_id":68897134,"title":"Lepidote simple wirewrap necklace","description":"Made to order lepidolite necklace \nVery calming mineral great for everyday wear. Made with love.\n\nPic is an example of the piece you will receive.\n\nThank u ","creation_tsz":1415054013,"ending_tsz":1425422013,"original_creation_tsz":1414848006,"last_modified_tsz":1415054013,"price":"45.00","currency_code":"USD","quantity":5,"tags":["energy","handmade","wirewrap","jewelry"],"category_path":["Jewelry","Necklace","Wire Wrapped"],"category_path_ids":[68887482,69151567,68897134],"materials":["minerals","copper"],"shop_section_id":14779178,"featured_rank":null,"state_tsz":1414848006,"url":"https:\/\/www.etsy.com\/listing\/209305220\/lepidote-simple-wirewrap-necklace?utm_source=reworkcreativeonetsy&utm_medium=api&utm_campaign=api","views":122,"num_favorers":5,"shipping_template_id":3152165856,"processing_min":null,"processing_max":null,"who_made":"i_did","is_supply":"false","when_made":"made_to_order","is_private":false,"recipient":null,"occasion":null,"style":null,"non_taxable":false,"is_customizable":false,"is_digital":false,"file_data":"","language":"en-US","has_variations":false,"used_manufacturer":false,"Images":[{"listing_image_id":675390950,"hex_code":"808D8F","red":128,"green":141,"blue":143,"hue":188,"saturation":10,"brightness":56,"is_black_and_white":false,"creation_tsz":1414848006,"listing_id":209305220,"rank":1,"url_75x75":"https:\/\/img0.etsystatic.com\/048\/0\/5406120\/il_75x75.675390950_db2t.jpg","url_170x135":"https:\/\/img0.etsystatic.com\/048\/0\/5406120\/il_170x135.675390950_db2t.jpg","url_570xN":"https:\/\/img0.etsystatic.com\/048\/0\/5406120\/il_570xN.675390950_db2t.jpg","url_fullxfull":"https:\/\/img0.etsystatic.com\/048\/0\/5406120\/il_fullxfull.675390950_db2t.jpg","full_height":1500,"full_width":1500}]}],"params":{"limit":"100","offset":0,"page":null,"shop_id":"ReworkCreative","shop_section_id":"14779178","sort_on":"created","sort_order":"down"},"type":"Listing","pagination":{"effective_limit":100,"effective_offset":0,"next_offset":null,"effective_page":1,"next_page":null}}